package com.umeng.message.proguard;

public class Y
{
  // ERROR //
  public static java.util.Map<java.lang.String, Object> a(M.a parama)
  {
    // Byte code:
    //   0: aload_0
    //   1: ifnull +525 -> 526
    //   4: new 14	java/util/HashMap
    //   7: dup
    //   8: invokespecial 18	java/util/HashMap:<init>	()V
    //   11: astore 6
    //   13: aload_0
    //   14: invokevirtual 24	com/umeng/message/proguard/M$a:c	()Ljava/util/List;
    //   17: invokeinterface 30 1 0
    //   22: astore_0
    //   23: aload_0
    //   24: invokeinterface 36 1 0
    //   29: ifeq +121 -> 150
    //   32: aload_0
    //   33: invokeinterface 40 1 0
    //   38: checkcast 42	com/umeng/message/proguard/M$a$a
    //   41: astore_1
    //   42: aload_1
    //   43: invokevirtual 45	com/umeng/message/proguard/M$a$a:b	()Ljava/util/List;
    //   46: invokeinterface 30 1 0
    //   51: astore_2
    //   52: aload_2
    //   53: invokeinterface 36 1 0
    //   58: ifeq -35 -> 23
    //   61: aload_2
    //   62: invokeinterface 40 1 0
    //   67: checkcast 47	java/lang/String
    //   70: astore_3
    //   71: aload 6
    //   73: aload_3
    //   74: invokeinterface 53 2 0
    //   79: ifeq +55 -> 134
    //   82: aload 6
    //   84: aload_3
    //   85: invokeinterface 57 2 0
    //   90: checkcast 47	java/lang/String
    //   93: astore 4
    //   95: aload 6
    //   97: aload_3
    //   98: new 59	java/lang/StringBuilder
    //   101: dup
    //   102: invokespecial 60	java/lang/StringBuilder:<init>	()V
    //   105: aload 4
    //   107: invokevirtual 64	java/lang/StringBuilder:append	(Ljava/lang/String;)Ljava/lang/StringBuilder;
    //   110: ldc 66
    //   112: invokevirtual 64	java/lang/StringBuilder:append	(Ljava/lang/String;)Ljava/lang/StringBuilder;
    //   115: aload_1
    //   116: invokevirtual 69	com/umeng/message/proguard/M$a$a:a	()Ljava/lang/String;
    //   119: invokevirtual 64	java/lang/StringBuilder:append	(Ljava/lang/String;)Ljava/lang/StringBuilder;
    //   122: invokevirtual 72	java/lang/StringBuilder:toString	()Ljava/lang/String;
    //   125: invokeinterface 76 3 0
    //   130: pop
    //   131: goto -79 -> 52
    //   134: aload 6
    //   136: aload_3
    //   137: aload_1
    //   138: invokevirtual 69	com/umeng/message/proguard/M$a$a:a	()Ljava/lang/String;
    //   141: invokeinterface 76 3 0
    //   146: pop
    //   147: goto -95 -> 52
    //   150: aload 6
    //   152: ifnull +374 -> 526
    //   155: aload 6
    //   157: invokeinterface 80 1 0
    //   162: ifle +364 -> 526
    //   165: new 14	java/util/HashMap
    //   168: dup
    //   169: invokespecial 18	java/util/HashMap:<init>	()V
    //   172: astore 7
    //   174: aload 6
    //   176: ifnull +347 -> 523
    //   179: aload 6
    //   181: invokeinterface 80 1 0
    //   186: ifle +337 -> 523
    //   189: aload 6
    //   191: invokeinterface 84 1 0
    //   196: invokeinterface 87 1 0
    //   201: astore 8
    //   203: aload 8
    //   205: invokeinterface 36 1 0
    //   210: ifeq +313 -> 523
    //   213: aload 8
    //   215: invokeinterface 40 1 0
    //   220: checkcast 47	java/lang/String
    //   223: astore 4
    //   225: aload 6
    //   227: aload 4
    //   229: invokeinterface 57 2 0
    //   234: checkcast 47	java/lang/String
    //   237: astore 5
    //   239: aload 4
    //   241: invokestatic 92	com/umeng/message/proguard/at:a	(Ljava/lang/String;)Z
    //   244: ifne -41 -> 203
    //   247: aload 5
    //   249: invokestatic 92	com/umeng/message/proguard/at:a	(Ljava/lang/String;)Z
    //   252: ifne -49 -> 203
    //   255: new 94	java/io/ByteArrayOutputStream
    //   258: dup
    //   259: invokespecial 95	java/io/ByteArrayOutputStream:<init>	()V
    //   262: astore_0
    //   263: new 97	java/util/zip/GZIPOutputStream
    //   266: dup
    //   267: aload_0
    //   268: invokespecial 100	java/util/zip/GZIPOutputStream:<init>	(Ljava/io/OutputStream;)V
    //   271: astore_1
    //   272: aload_0
    //   273: astore_3
    //   274: aload_1
    //   275: astore_2
    //   276: aload_1
    //   277: aload 5
    //   279: ldc 102
    //   281: invokevirtual 106	java/lang/String:getBytes	(Ljava/lang/String;)[B
    //   284: invokevirtual 112	java/io/OutputStream:write	([B)V
    //   287: aload_0
    //   288: astore_3
    //   289: aload_1
    //   290: astore_2
    //   291: aload_1
    //   292: invokevirtual 115	java/io/OutputStream:flush	()V
    //   295: aload_0
    //   296: astore_3
    //   297: aload_1
    //   298: astore_2
    //   299: aload_1
    //   300: invokevirtual 118	java/io/OutputStream:close	()V
    //   303: aload_0
    //   304: astore_3
    //   305: aload_1
    //   306: astore_2
    //   307: aload 7
    //   309: aload 4
    //   311: aload_0
    //   312: invokevirtual 122	java/io/ByteArrayOutputStream:toByteArray	()[B
    //   315: invokestatic 126	com/umeng/message/proguard/t:b	()Ljava/lang/String;
    //   318: invokestatic 131	com/umeng/message/proguard/x:a	([BLjava/lang/String;)[B
    //   321: invokeinterface 76 3 0
    //   326: pop
    //   327: aload_0
    //   328: astore_3
    //   329: aload_1
    //   330: astore_2
    //   331: invokestatic 135	com/umeng/message/proguard/y:a	()Z
    //   334: ifeq +50 -> 384
    //   337: aload_0
    //   338: astore_3
    //   339: aload_1
    //   340: astore_2
    //   341: iconst_2
    //   342: new 59	java/lang/StringBuilder
    //   345: dup
    //   346: invokespecial 60	java/lang/StringBuilder:<init>	()V
    //   349: ldc 137
    //   351: invokevirtual 64	java/lang/StringBuilder:append	(Ljava/lang/String;)Ljava/lang/StringBuilder;
    //   354: aload 4
    //   356: invokevirtual 64	java/lang/StringBuilder:append	(Ljava/lang/String;)Ljava/lang/StringBuilder;
    //   359: ldc 139
    //   361: invokevirtual 64	java/lang/StringBuilder:append	(Ljava/lang/String;)Ljava/lang/StringBuilder;
    //   364: invokevirtual 72	java/lang/StringBuilder:toString	()Ljava/lang/String;
    //   367: ldc 141
    //   369: iconst_1
    //   370: anewarray 4	java/lang/Object
    //   373: dup
    //   374: iconst_0
    //   375: aload 5
    //   377: aastore
    //   378: invokestatic 145	java/lang/String:format	(Ljava/lang/String;[Ljava/lang/Object;)Ljava/lang/String;
    //   381: invokestatic 148	com/umeng/message/proguard/y:b	(ILjava/lang/String;Ljava/lang/Object;)V
    //   384: aload_1
    //   385: invokevirtual 118	java/io/OutputStream:close	()V
    //   388: aload_0
    //   389: invokevirtual 149	java/io/ByteArrayOutputStream:close	()V
    //   392: goto -189 -> 203
    //   395: astore_0
    //   396: aload_0
    //   397: invokevirtual 152	java/lang/Throwable:printStackTrace	()V
    //   400: goto -197 -> 203
    //   403: astore_1
    //   404: aload_1
    //   405: invokevirtual 152	java/lang/Throwable:printStackTrace	()V
    //   408: goto -20 -> 388
    //   411: astore_2
    //   412: aconst_null
    //   413: astore_0
    //   414: aconst_null
    //   415: astore_1
    //   416: aload_2
    //   417: invokevirtual 153	java/io/UnsupportedEncodingException:printStackTrace	()V
    //   420: aload_1
    //   421: invokevirtual 118	java/io/OutputStream:close	()V
    //   424: aload_0
    //   425: invokevirtual 149	java/io/ByteArrayOutputStream:close	()V
    //   428: goto -225 -> 203
    //   431: astore_0
    //   432: aload_0
    //   433: invokevirtual 152	java/lang/Throwable:printStackTrace	()V
    //   436: goto -233 -> 203
    //   439: astore_1
    //   440: aload_1
    //   441: invokevirtual 152	java/lang/Throwable:printStackTrace	()V
    //   444: goto -20 -> 424
    //   447: astore 5
    //   449: aconst_null
    //   450: astore 4
    //   452: aconst_null
    //   453: astore_0
    //   454: aload 4
    //   456: astore_3
    //   457: aload_0
    //   458: astore_2
    //   459: aload 5
    //   461: invokevirtual 154	java/lang/Exception:printStackTrace	()V
    //   464: aload_0
    //   465: invokevirtual 118	java/io/OutputStream:close	()V
    //   468: aload 4
    //   470: invokevirtual 149	java/io/ByteArrayOutputStream:close	()V
    //   473: goto -270 -> 203
    //   476: astore_0
    //   477: aload_0
    //   478: invokevirtual 152	java/lang/Throwable:printStackTrace	()V
    //   481: goto -278 -> 203
    //   484: astore_0
    //   485: aload_0
    //   486: invokevirtual 152	java/lang/Throwable:printStackTrace	()V
    //   489: goto -21 -> 468
    //   492: astore_1
    //   493: aconst_null
    //   494: astore_0
    //   495: aconst_null
    //   496: astore_2
    //   497: aload_2
    //   498: invokevirtual 118	java/io/OutputStream:close	()V
    //   501: aload_0
    //   502: invokevirtual 149	java/io/ByteArrayOutputStream:close	()V
    //   505: aload_1
    //   506: athrow
    //   507: astore_2
    //   508: aload_2
    //   509: invokevirtual 152	java/lang/Throwable:printStackTrace	()V
    //   512: goto -11 -> 501
    //   515: astore_0
    //   516: aload_0
    //   517: invokevirtual 152	java/lang/Throwable:printStackTrace	()V
    //   520: goto -15 -> 505
    //   523: aload 7
    //   525: areturn
    //   526: aconst_null
    //   527: areturn
    //   528: astore_1
    //   529: aconst_null
    //   530: astore_2
    //   531: goto -34 -> 497
    //   534: astore_1
    //   535: aload_3
    //   536: astore_0
    //   537: goto -40 -> 497
    //   540: astore_3
    //   541: aload_1
    //   542: astore_2
    //   543: aload_3
    //   544: astore_1
    //   545: goto -48 -> 497
    //   548: astore 5
    //   550: aconst_null
    //   551: astore_1
    //   552: aload_0
    //   553: astore 4
    //   555: aload_1
    //   556: astore_0
    //   557: goto -103 -> 454
    //   560: astore 5
    //   562: aload_0
    //   563: astore 4
    //   565: aload_1
    //   566: astore_0
    //   567: goto -113 -> 454
    //   570: astore_2
    //   571: aconst_null
    //   572: astore_1
    //   573: goto -157 -> 416
    //   576: astore_2
    //   577: goto -161 -> 416
    //
    // Exception table:
    //   from	to	target	type
    //   388	392	395	java/lang/Throwable
    //   384	388	403	java/lang/Throwable
    //   255	263	411	java/io/UnsupportedEncodingException
    //   424	428	431	java/lang/Throwable
    //   420	424	439	java/lang/Throwable
    //   255	263	447	java/lang/Exception
    //   468	473	476	java/lang/Throwable
    //   464	468	484	java/lang/Throwable
    //   255	263	492	finally
    //   497	501	507	java/lang/Throwable
    //   501	505	515	java/lang/Throwable
    //   263	272	528	finally
    //   276	287	534	finally
    //   291	295	534	finally
    //   299	303	534	finally
    //   307	327	534	finally
    //   331	337	534	finally
    //   341	384	534	finally
    //   459	464	534	finally
    //   416	420	540	finally
    //   263	272	548	java/lang/Exception
    //   276	287	560	java/lang/Exception
    //   291	295	560	java/lang/Exception
    //   299	303	560	java/lang/Exception
    //   307	327	560	java/lang/Exception
    //   331	337	560	java/lang/Exception
    //   341	384	560	java/lang/Exception
    //   263	272	570	java/io/UnsupportedEncodingException
    //   276	287	576	java/io/UnsupportedEncodingException
    //   291	295	576	java/io/UnsupportedEncodingException
    //   299	303	576	java/io/UnsupportedEncodingException
    //   307	327	576	java/io/UnsupportedEncodingException
    //   331	337	576	java/io/UnsupportedEncodingException
    //   341	384	576	java/io/UnsupportedEncodingException
  }
}

/* Location:           F:\一周备份\面试apk\希望代码没混淆\jingmgou\jingmgou2\classes-dex2jar.jar
 * Qualified Name:     com.umeng.message.proguard.Y
 * JD-Core Version:    0.6.2
 */