package cn.jpush.android.service;

public final class o extends Thread
{
  private static final String[] z;
  boolean a = true;
  private volatile boolean c = false;

  static
  {
    String[] arrayOfString = new String[41];
    int j = 0;
    Object localObject2 = "\016\031FP\0242\035Z\003L^";
    int i = -1;
    Object localObject1 = arrayOfString;
    char[] arrayOfChar = ((String)localObject2).toCharArray();
    int k = arrayOfChar.length;
    int i1 = 0;
    int m = 0;
    int i3 = i;
    localObject2 = arrayOfChar;
    int i4 = j;
    Object localObject3 = localObject1;
    int n = k;
    Object localObject4;
    int i2;
    if (k <= 1)
    {
      localObject4 = localObject1;
      localObject1 = arrayOfChar;
      i2 = i;
      label68: n = m;
      label71: localObject2 = localObject1;
      i1 = localObject2[m];
      switch (n % 5)
      {
      default:
        i = 113;
      case 0:
      case 1:
      case 2:
      case 3:
      }
    }
    while (true)
    {
      localObject2[m] = ((char)(i ^ i1));
      n += 1;
      if (k == 0)
      {
        m = k;
        break label71;
      }
      i1 = n;
      n = k;
      localObject3 = localObject4;
      i4 = j;
      localObject2 = localObject1;
      i3 = i2;
      i2 = i3;
      localObject1 = localObject2;
      j = i4;
      localObject4 = localObject3;
      k = n;
      m = i1;
      if (n > i1)
        break label68;
      localObject1 = new String((char[])localObject2).intern();
      switch (i3)
      {
      default:
        localObject3[i4] = localObject1;
        j = 1;
        localObject2 = "\022\027SJ\037^\036UJ\035^B\024P\036\f\fkH\024\007X\t\003";
        i = 0;
        localObject1 = arrayOfString;
        break;
      case 0:
        localObject3[i4] = localObject1;
        j = 2;
        localObject2 = "\022\027SJ\037^\036UJ\035^B\024W\036\n\027Xo\024\020X\t\003";
        i = 1;
        localObject1 = arrayOfString;
        break;
      case 1:
        localObject3[i4] = localObject1;
        j = 3;
        localObject2 = "\r\016QQ\002\027\027Z\003L^";
        i = 2;
        localObject1 = arrayOfString;
        break;
      case 2:
        localObject3[i4] = localObject1;
        j = 4;
        localObject2 = "";
        i = 3;
        localObject1 = arrayOfString;
        break;
      case 3:
        localObject3[i4] = localObject1;
        j = 5;
        localObject2 = "\r\f]N\024^E\024";
        i = 4;
        localObject1 = arrayOfString;
        break;
      case 4:
        localObject3[i4] = localObject1;
        j = 6;
        localObject2 = "\r\035FU\024\f,]N\024^E\024";
        i = 5;
        localObject1 = arrayOfString;
        break;
      case 5:
        localObject3[i4] = localObject1;
        j = 7;
        localObject2 = "3<\001";
        i = 6;
        localObject1 = arrayOfString;
        break;
      case 6:
        localObject3[i4] = localObject1;
        j = 8;
        localObject2 = "^X\024\003Q^X\024\003Q^\024[D\030\020'WL\002\n\021YFK^";
        i = 7;
        localObject1 = arrayOfString;
        break;
      case 7:
        localObject3[i4] = localObject1;
        j = 9;
        localObject2 = "2\027SJ\037DXYj\025^E\024\006\025RXdB\002\r\017[Q\025^\025P\026QCX\021P";
        i = 8;
        localObject1 = arrayOfString;
        break;
      case 8:
        localObject3[i4] = localObject1;
        j = 10;
        localObject2 = "\r\021P\003L^";
        i = 9;
        localObject1 = arrayOfString;
        break;
      case 9:
        localObject3[i4] = localObject1;
        j = 11;
        localObject2 = "\022\027SJ\037!\013QQ\007\033\nkW\030\023\035";
        i = 10;
        localObject1 = arrayOfString;
        break;
      case 10:
        localObject3[i4] = localObject1;
        j = 12;
        localObject2 = "^\033UM\037\021\f\024S\020\f\013Q\003\002\033\nBF\003*\021YFQ";
        i = 11;
        localObject1 = arrayOfString;
        break;
      case 11:
        localObject3[i4] = localObject1;
        j = 13;
        localObject2 = "^E\024";
        i = 12;
        localObject1 = arrayOfString;
        break;
      case 12:
        localObject3[i4] = localObject1;
        j = 14;
        localObject2 = "2\027SJ\037C]P)";
        i = 13;
        localObject1 = arrayOfString;
        break;
      case 13:
        localObject3[i4] = localObject1;
        j = 15;
        localObject2 = "OV\f\rC";
        i = 14;
        localObject1 = arrayOfString;
        break;
      case 14:
        localObject3[i4] = localObject1;
        j = 16;
        localObject2 = "^X\024W\036\n\031Xo\024\020X\t\003";
        i = 15;
        localObject1 = arrayOfString;
        break;
      case 15:
        localObject3[i4] = localObject1;
        j = 17;
        localObject2 = "^U\024";
        i = 16;
        localObject1 = arrayOfString;
        break;
      case 16:
        localObject3[i4] = localObject1;
        j = 18;
        localObject2 = "[H\006{";
        i = 17;
        localObject1 = arrayOfString;
        break;
      case 17:
        localObject3[i4] = localObject1;
        j = 19;
        localObject2 = "\r\027FW.\025\035M\003K^";
        i = 18;
        localObject1 = arrayOfString;
        break;
      case 18:
        localObject3[i4] = localObject1;
        j = 20;
        localObject2 = "\022\027SJ\037<\rRE\024\fX\t\003";
        i = 19;
        localObject1 = arrayOfString;
        break;
      case 19:
        localObject3[i4] = localObject1;
        j = 21;
        localObject2 = "\r\027FW.\025\035M\031";
        i = 20;
        localObject1 = arrayOfString;
        break;
      case 20:
        localObject3[i4] = localObject1;
        j = 22;
        localObject2 = "^\f[W\036\0224QMQCX";
        i = 21;
        localObject1 = arrayOfString;
        break;
      case 21:
        localObject3[i4] = localObject1;
        j = 23;
        localObject2 = "\022\027SJ\037^\036UJ\035^B\024o\036\031\021Z\036";
        i = 22;
        localObject1 = arrayOfString;
        break;
      case 22:
        localObject3[i4] = localObject1;
        j = 24;
        localObject2 = "^X\024\003\003\033\b[Q\005*\021YFQCX";
        i = 23;
        localObject1 = arrayOfString;
        break;
      case 23:
        localObject3[i4] = localObject1;
        j = 25;
        localObject2 = ".\rGK\"\033\nBJ\022\033";
        i = 24;
        localObject1 = arrayOfString;
        break;
      case 24:
        localObject3[i4] = localObject1;
        j = 26;
        localObject2 = "\f\035@\003L^";
        i = 25;
        localObject1 = arrayOfString;
        break;
      case 25:
        localObject3[i4] = localObject1;
        j = 27;
        localObject2 = "\"V";
        i = 26;
        localObject1 = arrayOfString;
        break;
      case 26:
        localObject3[i4] = localObject1;
        j = 28;
        localObject2 = "\022\027SJ\037!\nQS\036\f\fkW\030\023\035";
        i = 27;
        localObject1 = arrayOfString;
        break;
      case 27:
        localObject3[i4] = localObject1;
        j = 29;
        localObject2 = "^X\024@\036\023\025UM\025^E\024";
        i = 28;
        localObject1 = arrayOfString;
        break;
      case 28:
        localObject3[i4] = localObject1;
        j = 30;
        localObject2 = "^\021G\003\024\006\021GW\002^B\024V\001\032\031@F";
        i = 29;
        localObject1 = arrayOfString;
        break;
      case 29:
        localObject3[i4] = localObject1;
        j = 31;
        localObject2 = "\r\fFh\024\007X\t\003";
        i = 30;
        localObject1 = arrayOfString;
        break;
      case 30:
        localObject3[i4] = localObject1;
        j = 32;
        localObject2 = "\035\026\032I\001\013\013\\\r\020\020\034FL\030\032V]M\005\033\026@\r216zf2*1{m";
        i = 31;
        localObject1 = arrayOfString;
        break;
      case 31:
        localObject3[i4] = localObject1;
        j = 33;
        localObject2 = "2\027SJ\037^\036UJ\035\033\034\030\003\005\026\nQB\0257\034\024\036Q";
        i = 32;
        localObject1 = arrayOfString;
        break;
      case 32:
        localObject3[i4] = localObject1;
        j = 34;
        localObject2 = ";\026@F\003^\033[M\037\033\033@J\036\020X@K\003\033\031Pj\025^E\024";
        i = 33;
        localObject1 = arrayOfString;
        break;
      case 33:
        localObject3[i4] = localObject1;
        j = 35;
        localObject2 = "2\027SJ\037^\036UJ\035\033\034\016\003";
        i = 34;
        localObject1 = arrayOfString;
        break;
      case 34:
        localObject3[i4] = localObject1;
        j = 36;
        localObject2 = "2\027SJ\037^\013A@\022\033\035P\002Q\f\035SJ\002\n\nUW\030\021\026}gL";
        i = 35;
        localObject1 = arrayOfString;
        break;
      case 35:
        localObject3[i4] = localObject1;
        j = 37;
        localObject2 = ",\035WUL[\034";
        i = 36;
        localObject1 = arrayOfString;
        break;
      case 36:
        localObject3[i4] = localObject1;
        j = 38;
        localObject2 = "7\026]WL[\034>";
        i = 37;
        localObject1 = arrayOfString;
        break;
      case 37:
        localObject3[i4] = localObject1;
        j = 39;
        localObject2 = "";
        i = 38;
        localObject1 = arrayOfString;
        break;
      case 38:
        localObject3[i4] = localObject1;
        j = 40;
        localObject2 = "\035\nQB\005\033XGL\022\025\035@\003\027\037\024]F\025^\017]W\031^\f\\Q\024\037\034}GQCX";
        i = 39;
        localObject1 = arrayOfString;
        break;
      case 39:
        localObject3[i4] = localObject1;
        z = arrayOfString;
        return;
        i = 126;
        continue;
        i = 120;
        continue;
        i = 52;
        continue;
        i = 35;
      }
    }
  }

  public o(PushService paramPushService)
  {
  }

  // ERROR //
  private int a()
  {
    // Byte code:
    //   0: getstatic 111	cn/jpush/android/service/o:z	[Ljava/lang/String;
    //   3: bipush 7
    //   5: aaload
    //   6: invokestatic 130	java/security/MessageDigest:getInstance	(Ljava/lang/String;)Ljava/security/MessageDigest;
    //   9: getstatic 136	cn/jpush/android/service/PushService:u	Ljava/lang/String;
    //   12: invokevirtual 140	java/lang/String:getBytes	()[B
    //   15: invokevirtual 144	java/security/MessageDigest:digest	([B)[B
    //   18: astore 17
    //   20: new 146	java/lang/StringBuilder
    //   23: dup
    //   24: aload 17
    //   26: arraylength
    //   27: iconst_2
    //   28: imul
    //   29: invokespecial 149	java/lang/StringBuilder:<init>	(I)V
    //   32: astore 18
    //   34: aload 17
    //   36: arraylength
    //   37: istore_3
    //   38: iconst_0
    //   39: istore_2
    //   40: iload_2
    //   41: iload_3
    //   42: if_icmpge +41 -> 83
    //   45: aload 17
    //   47: iload_2
    //   48: baload
    //   49: istore_1
    //   50: aload 18
    //   52: getstatic 111	cn/jpush/android/service/o:z	[Ljava/lang/String;
    //   55: bipush 18
    //   57: aaload
    //   58: iconst_1
    //   59: anewarray 151	java/lang/Object
    //   62: dup
    //   63: iconst_0
    //   64: iload_1
    //   65: invokestatic 157	java/lang/Byte:valueOf	(B)Ljava/lang/Byte;
    //   68: aastore
    //   69: invokestatic 161	java/lang/String:format	(Ljava/lang/String;[Ljava/lang/Object;)Ljava/lang/String;
    //   72: invokevirtual 165	java/lang/StringBuilder:append	(Ljava/lang/String;)Ljava/lang/StringBuilder;
    //   75: pop
    //   76: iload_2
    //   77: iconst_1
    //   78: iadd
    //   79: istore_2
    //   80: goto -40 -> 40
    //   83: aload 18
    //   85: invokevirtual 168	java/lang/StringBuilder:toString	()Ljava/lang/String;
    //   88: astore 19
    //   90: getstatic 111	cn/jpush/android/service/o:z	[Ljava/lang/String;
    //   93: bipush 9
    //   95: aaload
    //   96: iconst_2
    //   97: anewarray 151	java/lang/Object
    //   100: dup
    //   101: iconst_0
    //   102: getstatic 172	cn/jpush/android/service/PushService:t	J
    //   105: invokestatic 177	java/lang/Long:valueOf	(J)Ljava/lang/Long;
    //   108: aastore
    //   109: dup
    //   110: iconst_1
    //   111: aload 19
    //   113: aastore
    //   114: invokestatic 161	java/lang/String:format	(Ljava/lang/String;[Ljava/lang/Object;)Ljava/lang/String;
    //   117: pop
    //   118: invokestatic 181	cn/jpush/android/util/x:c	()V
    //   121: getstatic 111	cn/jpush/android/service/o:z	[Ljava/lang/String;
    //   124: bipush 15
    //   126: aaload
    //   127: getstatic 111	cn/jpush/android/service/o:z	[Ljava/lang/String;
    //   130: bipush 27
    //   132: aaload
    //   133: invokevirtual 185	java/lang/String:split	(Ljava/lang/String;)[Ljava/lang/String;
    //   136: astore 17
    //   138: aload 17
    //   140: iconst_0
    //   141: aaload
    //   142: invokestatic 191	java/lang/Integer:parseInt	(Ljava/lang/String;)I
    //   145: istore_2
    //   146: aload 17
    //   148: iconst_1
    //   149: aaload
    //   150: invokestatic 191	java/lang/Integer:parseInt	(Ljava/lang/String;)I
    //   153: istore_3
    //   154: aload 17
    //   156: iconst_2
    //   157: aaload
    //   158: invokestatic 191	java/lang/Integer:parseInt	(Ljava/lang/String;)I
    //   161: istore 4
    //   163: new 146	java/lang/StringBuilder
    //   166: dup
    //   167: getstatic 196	cn/jpush/android/a:f	Ljava/lang/String;
    //   170: invokevirtual 199	java/lang/String:length	()I
    //   173: invokespecial 149	java/lang/StringBuilder:<init>	(I)V
    //   176: astore 17
    //   178: aload 17
    //   180: getstatic 196	cn/jpush/android/a:f	Ljava/lang/String;
    //   183: invokevirtual 165	java/lang/StringBuilder:append	(Ljava/lang/String;)Ljava/lang/StringBuilder;
    //   186: pop
    //   187: aload 17
    //   189: invokevirtual 168	java/lang/StringBuilder:toString	()Ljava/lang/String;
    //   192: astore 20
    //   194: aload_0
    //   195: getfield 115	cn/jpush/android/service/o:b	Lcn/jpush/android/service/PushService;
    //   198: getfield 202	cn/jpush/android/service/PushService:w	J
    //   201: lconst_0
    //   202: lcmp
    //   203: ifeq +1318 -> 1521
    //   206: invokestatic 181	cn/jpush/android/util/x:c	()V
    //   209: aload_0
    //   210: getfield 115	cn/jpush/android/service/o:b	Lcn/jpush/android/service/PushService;
    //   213: invokevirtual 206	cn/jpush/android/service/PushService:getApplicationContext	()Landroid/content/Context;
    //   216: invokestatic 212	cn/jpush/android/util/a:v	(Landroid/content/Context;)Ljava/lang/String;
    //   219: astore 18
    //   221: sipush 128
    //   224: newarray byte
    //   226: astore 17
    //   228: invokestatic 218	java/lang/System:currentTimeMillis	()J
    //   231: lstore 11
    //   233: aload_0
    //   234: getfield 115	cn/jpush/android/service/o:b	Lcn/jpush/android/service/PushService;
    //   237: getfield 202	cn/jpush/android/service/PushService:w	J
    //   240: aload 17
    //   242: getstatic 172	cn/jpush/android/service/PushService:t	J
    //   245: aload 19
    //   247: aload 20
    //   249: iload 4
    //   251: iload_2
    //   252: bipush 16
    //   254: ishl
    //   255: iload_3
    //   256: bipush 8
    //   258: ishl
    //   259: iadd
    //   260: iadd
    //   261: i2l
    //   262: invokestatic 224	cn/jpush/android/service/PushProtocol:LogPushWithBack	(J[BJLjava/lang/String;Ljava/lang/String;J)I
    //   265: istore 8
    //   267: new 146	java/lang/StringBuilder
    //   270: dup
    //   271: invokespecial 225	java/lang/StringBuilder:<init>	()V
    //   274: aload 18
    //   276: invokevirtual 165	java/lang/StringBuilder:append	(Ljava/lang/String;)Ljava/lang/StringBuilder;
    //   279: ldc 227
    //   281: invokevirtual 165	java/lang/StringBuilder:append	(Ljava/lang/String;)Ljava/lang/StringBuilder;
    //   284: iload 8
    //   286: invokevirtual 230	java/lang/StringBuilder:append	(I)Ljava/lang/StringBuilder;
    //   289: ldc 227
    //   291: invokevirtual 165	java/lang/StringBuilder:append	(Ljava/lang/String;)Ljava/lang/StringBuilder;
    //   294: invokestatic 232	cn/jpush/android/service/PushService:b	()Ljava/lang/String;
    //   297: invokevirtual 165	java/lang/StringBuilder:append	(Ljava/lang/String;)Ljava/lang/StringBuilder;
    //   300: ldc 227
    //   302: invokevirtual 165	java/lang/StringBuilder:append	(Ljava/lang/String;)Ljava/lang/StringBuilder;
    //   305: invokestatic 235	cn/jpush/android/util/a:d	()Ljava/lang/String;
    //   308: invokevirtual 165	java/lang/StringBuilder:append	(Ljava/lang/String;)Ljava/lang/StringBuilder;
    //   311: invokevirtual 168	java/lang/StringBuilder:toString	()Ljava/lang/String;
    //   314: astore 20
    //   316: invokestatic 218	java/lang/System:currentTimeMillis	()J
    //   319: lstore 15
    //   321: lload 15
    //   323: lload 11
    //   325: lsub
    //   326: lstore 13
    //   328: new 146	java/lang/StringBuilder
    //   331: dup
    //   332: getstatic 111	cn/jpush/android/service/o:z	[Ljava/lang/String;
    //   335: bipush 19
    //   337: aaload
    //   338: invokespecial 238	java/lang/StringBuilder:<init>	(Ljava/lang/String;)V
    //   341: aload 20
    //   343: invokevirtual 165	java/lang/StringBuilder:append	(Ljava/lang/String;)Ljava/lang/StringBuilder;
    //   346: getstatic 111	cn/jpush/android/service/o:z	[Ljava/lang/String;
    //   349: bipush 8
    //   351: aaload
    //   352: invokevirtual 165	java/lang/StringBuilder:append	(Ljava/lang/String;)Ljava/lang/StringBuilder;
    //   355: lload 15
    //   357: invokevirtual 241	java/lang/StringBuilder:append	(J)Ljava/lang/StringBuilder;
    //   360: getstatic 111	cn/jpush/android/service/o:z	[Ljava/lang/String;
    //   363: bipush 17
    //   365: aaload
    //   366: invokevirtual 165	java/lang/StringBuilder:append	(Ljava/lang/String;)Ljava/lang/StringBuilder;
    //   369: lload 11
    //   371: invokevirtual 241	java/lang/StringBuilder:append	(J)Ljava/lang/StringBuilder;
    //   374: getstatic 111	cn/jpush/android/service/o:z	[Ljava/lang/String;
    //   377: bipush 13
    //   379: aaload
    //   380: invokevirtual 165	java/lang/StringBuilder:append	(Ljava/lang/String;)Ljava/lang/StringBuilder;
    //   383: lload 13
    //   385: invokevirtual 241	java/lang/StringBuilder:append	(J)Ljava/lang/StringBuilder;
    //   388: invokevirtual 168	java/lang/StringBuilder:toString	()Ljava/lang/String;
    //   391: pop
    //   392: invokestatic 181	cn/jpush/android/util/x:c	()V
    //   395: iload 8
    //   397: ifeq +11 -> 408
    //   400: iload 8
    //   402: sipush 9999
    //   405: if_icmpne +936 -> 1341
    //   408: aload 17
    //   410: invokestatic 244	cn/jpush/android/util/a:b	([B)I
    //   413: istore_2
    //   414: aload 17
    //   416: invokestatic 246	cn/jpush/android/util/a:c	([B)I
    //   419: istore 4
    //   421: new 146	java/lang/StringBuilder
    //   424: dup
    //   425: getstatic 111	cn/jpush/android/service/o:z	[Ljava/lang/String;
    //   428: bipush 26
    //   430: aaload
    //   431: invokespecial 238	java/lang/StringBuilder:<init>	(Ljava/lang/String;)V
    //   434: iload 8
    //   436: invokevirtual 230	java/lang/StringBuilder:append	(I)Ljava/lang/StringBuilder;
    //   439: getstatic 111	cn/jpush/android/service/o:z	[Ljava/lang/String;
    //   442: bipush 29
    //   444: aaload
    //   445: invokevirtual 165	java/lang/StringBuilder:append	(Ljava/lang/String;)Ljava/lang/StringBuilder;
    //   448: iload_2
    //   449: invokevirtual 230	java/lang/StringBuilder:append	(I)Ljava/lang/StringBuilder;
    //   452: getstatic 111	cn/jpush/android/service/o:z	[Ljava/lang/String;
    //   455: bipush 22
    //   457: aaload
    //   458: invokevirtual 165	java/lang/StringBuilder:append	(Ljava/lang/String;)Ljava/lang/StringBuilder;
    //   461: iload 4
    //   463: invokevirtual 230	java/lang/StringBuilder:append	(I)Ljava/lang/StringBuilder;
    //   466: invokevirtual 168	java/lang/StringBuilder:toString	()Ljava/lang/String;
    //   469: pop
    //   470: invokestatic 248	cn/jpush/android/util/x:d	()V
    //   473: new 146	java/lang/StringBuilder
    //   476: dup
    //   477: getstatic 111	cn/jpush/android/service/o:z	[Ljava/lang/String;
    //   480: bipush 20
    //   482: aaload
    //   483: invokespecial 238	java/lang/StringBuilder:<init>	(Ljava/lang/String;)V
    //   486: aload 17
    //   488: iload 4
    //   490: invokestatic 251	cn/jpush/android/service/PushService:a	([BI)Ljava/lang/String;
    //   493: invokevirtual 165	java/lang/StringBuilder:append	(Ljava/lang/String;)Ljava/lang/StringBuilder;
    //   496: invokevirtual 168	java/lang/StringBuilder:toString	()Ljava/lang/String;
    //   499: pop
    //   500: invokestatic 248	cn/jpush/android/util/x:d	()V
    //   503: iload 4
    //   505: bipush 34
    //   507: if_icmpge +41 -> 548
    //   510: getstatic 111	cn/jpush/android/service/o:z	[Ljava/lang/String;
    //   513: bipush 25
    //   515: aaload
    //   516: new 146	java/lang/StringBuilder
    //   519: dup
    //   520: getstatic 111	cn/jpush/android/service/o:z	[Ljava/lang/String;
    //   523: iconst_2
    //   524: aaload
    //   525: invokespecial 238	java/lang/StringBuilder:<init>	(Ljava/lang/String;)V
    //   528: iload 4
    //   530: invokevirtual 230	java/lang/StringBuilder:append	(I)Ljava/lang/StringBuilder;
    //   533: getstatic 111	cn/jpush/android/service/o:z	[Ljava/lang/String;
    //   536: bipush 12
    //   538: aaload
    //   539: invokevirtual 165	java/lang/StringBuilder:append	(Ljava/lang/String;)Ljava/lang/StringBuilder;
    //   542: invokevirtual 168	java/lang/StringBuilder:toString	()Ljava/lang/String;
    //   545: invokestatic 255	cn/jpush/android/util/x:e	(Ljava/lang/String;Ljava/lang/String;)V
    //   548: iconst_0
    //   549: istore_3
    //   550: iconst_0
    //   551: istore_2
    //   552: iload_2
    //   553: iconst_2
    //   554: if_icmpge +27 -> 581
    //   557: iload_3
    //   558: bipush 8
    //   560: ishl
    //   561: aload 17
    //   563: iload_2
    //   564: bipush 20
    //   566: iadd
    //   567: baload
    //   568: sipush 255
    //   571: iand
    //   572: iadd
    //   573: istore_3
    //   574: iload_2
    //   575: iconst_1
    //   576: iadd
    //   577: istore_2
    //   578: goto -26 -> 552
    //   581: iload_3
    //   582: ifne +403 -> 985
    //   585: lconst_0
    //   586: lstore 11
    //   588: iconst_0
    //   589: istore_2
    //   590: iload_2
    //   591: iconst_4
    //   592: if_icmpge +30 -> 622
    //   595: lload 11
    //   597: bipush 8
    //   599: lshl
    //   600: aload 17
    //   602: iload_2
    //   603: bipush 22
    //   605: iadd
    //   606: baload
    //   607: sipush 255
    //   610: iand
    //   611: i2l
    //   612: ladd
    //   613: lstore 11
    //   615: iload_2
    //   616: iconst_1
    //   617: iadd
    //   618: istore_2
    //   619: goto -29 -> 590
    //   622: new 146	java/lang/StringBuilder
    //   625: dup
    //   626: getstatic 111	cn/jpush/android/service/o:z	[Ljava/lang/String;
    //   629: bipush 10
    //   631: aaload
    //   632: invokespecial 238	java/lang/StringBuilder:<init>	(Ljava/lang/String;)V
    //   635: lload 11
    //   637: invokevirtual 241	java/lang/StringBuilder:append	(J)Ljava/lang/StringBuilder;
    //   640: invokevirtual 168	java/lang/StringBuilder:toString	()Ljava/lang/String;
    //   643: pop
    //   644: invokestatic 248	cn/jpush/android/util/x:d	()V
    //   647: iconst_0
    //   648: istore_3
    //   649: iconst_0
    //   650: istore_2
    //   651: iload_2
    //   652: iconst_2
    //   653: if_icmpge +27 -> 680
    //   656: iload_3
    //   657: bipush 8
    //   659: ishl
    //   660: aload 17
    //   662: iload_2
    //   663: bipush 26
    //   665: iadd
    //   666: baload
    //   667: sipush 255
    //   670: iand
    //   671: iadd
    //   672: istore_3
    //   673: iload_2
    //   674: iconst_1
    //   675: iadd
    //   676: istore_2
    //   677: goto -26 -> 651
    //   680: new 146	java/lang/StringBuilder
    //   683: dup
    //   684: getstatic 111	cn/jpush/android/service/o:z	[Ljava/lang/String;
    //   687: iconst_3
    //   688: aaload
    //   689: invokespecial 238	java/lang/StringBuilder:<init>	(Ljava/lang/String;)V
    //   692: iload_3
    //   693: invokevirtual 230	java/lang/StringBuilder:append	(I)Ljava/lang/StringBuilder;
    //   696: invokevirtual 168	java/lang/StringBuilder:toString	()Ljava/lang/String;
    //   699: pop
    //   700: invokestatic 248	cn/jpush/android/util/x:d	()V
    //   703: iconst_0
    //   704: istore_3
    //   705: iconst_0
    //   706: istore_2
    //   707: iload_3
    //   708: iconst_2
    //   709: if_icmpge +31 -> 740
    //   712: aload 17
    //   714: iload_3
    //   715: bipush 28
    //   717: iadd
    //   718: baload
    //   719: istore 5
    //   721: iload_3
    //   722: iconst_1
    //   723: iadd
    //   724: istore_3
    //   725: iload_2
    //   726: bipush 8
    //   728: ishl
    //   729: iload 5
    //   731: sipush 255
    //   734: iand
    //   735: iadd
    //   736: istore_2
    //   737: goto -30 -> 707
    //   740: iload_2
    //   741: newarray byte
    //   743: astore 19
    //   745: iconst_0
    //   746: istore_3
    //   747: iload_3
    //   748: aload 19
    //   750: arraylength
    //   751: if_icmpge +26 -> 777
    //   754: aload 19
    //   756: iload_3
    //   757: aload 17
    //   759: iload_3
    //   760: bipush 30
    //   762: iadd
    //   763: baload
    //   764: sipush 255
    //   767: iand
    //   768: i2b
    //   769: bastore
    //   770: iload_3
    //   771: iconst_1
    //   772: iadd
    //   773: istore_3
    //   774: goto -27 -> 747
    //   777: new 15	java/lang/String
    //   780: dup
    //   781: aload 19
    //   783: invokespecial 258	java/lang/String:<init>	([B)V
    //   786: astore 19
    //   788: new 146	java/lang/StringBuilder
    //   791: dup
    //   792: getstatic 111	cn/jpush/android/service/o:z	[Ljava/lang/String;
    //   795: bipush 31
    //   797: aaload
    //   798: invokespecial 238	java/lang/StringBuilder:<init>	(Ljava/lang/String;)V
    //   801: aload 19
    //   803: invokevirtual 165	java/lang/StringBuilder:append	(Ljava/lang/String;)Ljava/lang/StringBuilder;
    //   806: invokevirtual 168	java/lang/StringBuilder:toString	()Ljava/lang/String;
    //   809: pop
    //   810: invokestatic 248	cn/jpush/android/util/x:d	()V
    //   813: iload_2
    //   814: bipush 30
    //   816: iadd
    //   817: istore_3
    //   818: lconst_0
    //   819: lstore 11
    //   821: iconst_0
    //   822: istore_2
    //   823: iload_2
    //   824: iconst_4
    //   825: if_icmpge +29 -> 854
    //   828: lload 11
    //   830: bipush 8
    //   832: lshl
    //   833: aload 17
    //   835: iload_3
    //   836: iload_2
    //   837: iadd
    //   838: baload
    //   839: sipush 255
    //   842: iand
    //   843: i2l
    //   844: ladd
    //   845: lstore 11
    //   847: iload_2
    //   848: iconst_1
    //   849: iadd
    //   850: istore_2
    //   851: goto -28 -> 823
    //   854: iload_3
    //   855: iconst_4
    //   856: iadd
    //   857: istore_2
    //   858: iload_2
    //   859: iload 4
    //   861: if_icmpne +440 -> 1301
    //   864: invokestatic 248	cn/jpush/android/util/x:d	()V
    //   867: lload 11
    //   869: putstatic 261	cn/jpush/android/service/PushService:m	J
    //   872: invokestatic 218	java/lang/System:currentTimeMillis	()J
    //   875: ldc2_w 262
    //   878: ldiv
    //   879: putstatic 266	cn/jpush/android/service/PushService:n	J
    //   882: new 146	java/lang/StringBuilder
    //   885: dup
    //   886: getstatic 111	cn/jpush/android/service/o:z	[Ljava/lang/String;
    //   889: iconst_5
    //   890: aaload
    //   891: invokespecial 238	java/lang/StringBuilder:<init>	(Ljava/lang/String;)V
    //   894: lload 11
    //   896: invokevirtual 241	java/lang/StringBuilder:append	(J)Ljava/lang/StringBuilder;
    //   899: invokevirtual 168	java/lang/StringBuilder:toString	()Ljava/lang/String;
    //   902: pop
    //   903: invokestatic 248	cn/jpush/android/util/x:d	()V
    //   906: new 146	java/lang/StringBuilder
    //   909: dup
    //   910: getstatic 111	cn/jpush/android/service/o:z	[Ljava/lang/String;
    //   913: bipush 6
    //   915: aaload
    //   916: invokespecial 238	java/lang/StringBuilder:<init>	(Ljava/lang/String;)V
    //   919: getstatic 261	cn/jpush/android/service/PushService:m	J
    //   922: invokevirtual 241	java/lang/StringBuilder:append	(J)Ljava/lang/StringBuilder;
    //   925: getstatic 111	cn/jpush/android/service/o:z	[Ljava/lang/String;
    //   928: bipush 24
    //   930: aaload
    //   931: invokevirtual 165	java/lang/StringBuilder:append	(Ljava/lang/String;)Ljava/lang/StringBuilder;
    //   934: getstatic 266	cn/jpush/android/service/PushService:n	J
    //   937: invokevirtual 241	java/lang/StringBuilder:append	(J)Ljava/lang/StringBuilder;
    //   940: invokevirtual 168	java/lang/StringBuilder:toString	()Ljava/lang/String;
    //   943: pop
    //   944: invokestatic 181	cn/jpush/android/util/x:c	()V
    //   947: aload_0
    //   948: getfield 115	cn/jpush/android/service/o:b	Lcn/jpush/android/service/PushService;
    //   951: invokevirtual 206	cn/jpush/android/service/PushService:getApplicationContext	()Landroid/content/Context;
    //   954: getstatic 111	cn/jpush/android/service/o:z	[Ljava/lang/String;
    //   957: bipush 11
    //   959: aaload
    //   960: getstatic 261	cn/jpush/android/service/PushService:m	J
    //   963: invokestatic 271	cn/jpush/android/util/ae:b	(Landroid/content/Context;Ljava/lang/String;J)V
    //   966: aload_0
    //   967: getfield 115	cn/jpush/android/service/o:b	Lcn/jpush/android/service/PushService;
    //   970: invokevirtual 206	cn/jpush/android/service/PushService:getApplicationContext	()Landroid/content/Context;
    //   973: getstatic 111	cn/jpush/android/service/o:z	[Ljava/lang/String;
    //   976: bipush 28
    //   978: aaload
    //   979: getstatic 266	cn/jpush/android/service/PushService:n	J
    //   982: invokestatic 271	cn/jpush/android/util/ae:b	(Landroid/content/Context;Ljava/lang/String;J)V
    //   985: iconst_0
    //   986: istore 4
    //   988: invokestatic 248	cn/jpush/android/util/x:d	()V
    //   991: iconst_0
    //   992: istore 5
    //   994: iconst_0
    //   995: istore_2
    //   996: iconst_0
    //   997: istore 6
    //   999: iconst_0
    //   1000: istore 10
    //   1002: iconst_0
    //   1003: istore 9
    //   1005: iload 9
    //   1007: istore 7
    //   1009: iload 4
    //   1011: ifne +68 -> 1079
    //   1014: lload 13
    //   1016: ldc2_w 262
    //   1019: lcmp
    //   1020: ifgt +5 -> 1025
    //   1023: iconst_1
    //   1024: istore_2
    //   1025: iload 10
    //   1027: istore_3
    //   1028: lload 13
    //   1030: ldc2_w 262
    //   1033: lcmp
    //   1034: ifle +17 -> 1051
    //   1037: iload 10
    //   1039: istore_3
    //   1040: lload 13
    //   1042: ldc2_w 272
    //   1045: lcmp
    //   1046: ifgt +5 -> 1051
    //   1049: iconst_1
    //   1050: istore_3
    //   1051: iload_2
    //   1052: istore 5
    //   1054: iload_3
    //   1055: istore 6
    //   1057: iload 9
    //   1059: istore 7
    //   1061: lload 13
    //   1063: ldc2_w 272
    //   1066: lcmp
    //   1067: ifle +12 -> 1079
    //   1070: iconst_1
    //   1071: istore 7
    //   1073: iload_3
    //   1074: istore 6
    //   1076: iload_2
    //   1077: istore 5
    //   1079: new 275	cn/jpush/android/data/u
    //   1082: dup
    //   1083: aload_0
    //   1084: getfield 115	cn/jpush/android/service/o:b	Lcn/jpush/android/service/PushService;
    //   1087: invokevirtual 206	cn/jpush/android/service/PushService:getApplicationContext	()Landroid/content/Context;
    //   1090: invokespecial 278	cn/jpush/android/data/u:<init>	(Landroid/content/Context;)V
    //   1093: astore 19
    //   1095: aload 19
    //   1097: ifnull +175 -> 1272
    //   1100: aload 19
    //   1102: invokevirtual 280	cn/jpush/android/data/u:a	()V
    //   1105: aload 19
    //   1107: aload 20
    //   1109: invokevirtual 283	cn/jpush/android/data/u:a	(Ljava/lang/String;)Z
    //   1112: ifeq +332 -> 1444
    //   1115: new 146	java/lang/StringBuilder
    //   1118: dup
    //   1119: getstatic 111	cn/jpush/android/service/o:z	[Ljava/lang/String;
    //   1122: bipush 21
    //   1124: aaload
    //   1125: invokespecial 238	java/lang/StringBuilder:<init>	(Ljava/lang/String;)V
    //   1128: aload 20
    //   1130: invokevirtual 165	java/lang/StringBuilder:append	(Ljava/lang/String;)Ljava/lang/StringBuilder;
    //   1133: getstatic 111	cn/jpush/android/service/o:z	[Ljava/lang/String;
    //   1136: bipush 30
    //   1138: aaload
    //   1139: invokevirtual 165	java/lang/StringBuilder:append	(Ljava/lang/String;)Ljava/lang/StringBuilder;
    //   1142: invokevirtual 168	java/lang/StringBuilder:toString	()Ljava/lang/String;
    //   1145: pop
    //   1146: invokestatic 248	cn/jpush/android/util/x:d	()V
    //   1149: aload 19
    //   1151: aload 20
    //   1153: invokevirtual 286	cn/jpush/android/data/u:b	(Ljava/lang/String;)Landroid/database/Cursor;
    //   1156: astore 17
    //   1158: aload 17
    //   1160: ifnonnull +6 -> 1166
    //   1163: invokestatic 288	cn/jpush/android/util/x:e	()V
    //   1166: aload 17
    //   1168: invokestatic 291	cn/jpush/android/data/u:a	(Landroid/database/Cursor;)Lcn/jpush/android/data/w;
    //   1171: astore 21
    //   1173: aload 21
    //   1175: ifnull +226 -> 1401
    //   1178: aload 19
    //   1180: aload 20
    //   1182: aload 18
    //   1184: invokestatic 232	cn/jpush/android/service/PushService:b	()Ljava/lang/String;
    //   1187: invokestatic 235	cn/jpush/android/util/a:d	()Ljava/lang/String;
    //   1190: new 146	java/lang/StringBuilder
    //   1193: dup
    //   1194: invokespecial 225	java/lang/StringBuilder:<init>	()V
    //   1197: iload 8
    //   1199: invokevirtual 230	java/lang/StringBuilder:append	(I)Ljava/lang/StringBuilder;
    //   1202: invokevirtual 168	java/lang/StringBuilder:toString	()Ljava/lang/String;
    //   1205: iload 4
    //   1207: aload 21
    //   1209: invokevirtual 295	cn/jpush/android/data/w:f	()I
    //   1212: iadd
    //   1213: aload 21
    //   1215: invokevirtual 298	cn/jpush/android/data/w:g	()I
    //   1218: iconst_1
    //   1219: iadd
    //   1220: iload 5
    //   1222: aload 21
    //   1224: invokevirtual 301	cn/jpush/android/data/w:h	()I
    //   1227: iadd
    //   1228: iload 6
    //   1230: aload 21
    //   1232: invokevirtual 304	cn/jpush/android/data/w:i	()I
    //   1235: iadd
    //   1236: iload 7
    //   1238: aload 21
    //   1240: invokevirtual 307	cn/jpush/android/data/w:j	()I
    //   1243: iadd
    //   1244: aload 21
    //   1246: invokevirtual 310	cn/jpush/android/data/w:k	()I
    //   1249: iconst_0
    //   1250: iadd
    //   1251: invokevirtual 313	cn/jpush/android/data/u:b	(Ljava/lang/String;Ljava/lang/String;Ljava/lang/String;Ljava/lang/String;Ljava/lang/String;IIIIII)Z
    //   1254: pop
    //   1255: aload 17
    //   1257: ifnull +10 -> 1267
    //   1260: aload 17
    //   1262: invokeinterface 318 1 0
    //   1267: aload 19
    //   1269: invokevirtual 320	cn/jpush/android/data/u:b	()V
    //   1272: iload 8
    //   1274: istore_2
    //   1275: getstatic 111	cn/jpush/android/service/o:z	[Ljava/lang/String;
    //   1278: bipush 14
    //   1280: aaload
    //   1281: iconst_1
    //   1282: anewarray 151	java/lang/Object
    //   1285: dup
    //   1286: iconst_0
    //   1287: iload_2
    //   1288: invokestatic 323	java/lang/Integer:valueOf	(I)Ljava/lang/Integer;
    //   1291: aastore
    //   1292: invokestatic 161	java/lang/String:format	(Ljava/lang/String;[Ljava/lang/Object;)Ljava/lang/String;
    //   1295: pop
    //   1296: invokestatic 181	cn/jpush/android/util/x:c	()V
    //   1299: iload_2
    //   1300: ireturn
    //   1301: new 146	java/lang/StringBuilder
    //   1304: dup
    //   1305: getstatic 111	cn/jpush/android/service/o:z	[Ljava/lang/String;
    //   1308: iconst_0
    //   1309: aaload
    //   1310: invokespecial 238	java/lang/StringBuilder:<init>	(Ljava/lang/String;)V
    //   1313: iload_2
    //   1314: invokevirtual 230	java/lang/StringBuilder:append	(I)Ljava/lang/StringBuilder;
    //   1317: getstatic 111	cn/jpush/android/service/o:z	[Ljava/lang/String;
    //   1320: bipush 16
    //   1322: aaload
    //   1323: invokevirtual 165	java/lang/StringBuilder:append	(Ljava/lang/String;)Ljava/lang/StringBuilder;
    //   1326: iload 4
    //   1328: invokevirtual 230	java/lang/StringBuilder:append	(I)Ljava/lang/StringBuilder;
    //   1331: invokevirtual 168	java/lang/StringBuilder:toString	()Ljava/lang/String;
    //   1334: pop
    //   1335: invokestatic 248	cn/jpush/android/util/x:d	()V
    //   1338: goto -471 -> 867
    //   1341: iconst_1
    //   1342: istore 4
    //   1344: getstatic 111	cn/jpush/android/service/o:z	[Ljava/lang/String;
    //   1347: bipush 25
    //   1349: aaload
    //   1350: new 146	java/lang/StringBuilder
    //   1353: dup
    //   1354: getstatic 111	cn/jpush/android/service/o:z	[Ljava/lang/String;
    //   1357: bipush 23
    //   1359: aaload
    //   1360: invokespecial 238	java/lang/StringBuilder:<init>	(Ljava/lang/String;)V
    //   1363: iload 8
    //   1365: invokevirtual 230	java/lang/StringBuilder:append	(I)Ljava/lang/StringBuilder;
    //   1368: invokevirtual 168	java/lang/StringBuilder:toString	()Ljava/lang/String;
    //   1371: invokestatic 255	cn/jpush/android/util/x:e	(Ljava/lang/String;Ljava/lang/String;)V
    //   1374: new 146	java/lang/StringBuilder
    //   1377: dup
    //   1378: getstatic 111	cn/jpush/android/service/o:z	[Ljava/lang/String;
    //   1381: iconst_1
    //   1382: aaload
    //   1383: invokespecial 238	java/lang/StringBuilder:<init>	(Ljava/lang/String;)V
    //   1386: aload 20
    //   1388: invokevirtual 165	java/lang/StringBuilder:append	(Ljava/lang/String;)Ljava/lang/StringBuilder;
    //   1391: invokevirtual 168	java/lang/StringBuilder:toString	()Ljava/lang/String;
    //   1394: pop
    //   1395: invokestatic 181	cn/jpush/android/util/x:c	()V
    //   1398: goto -410 -> 988
    //   1401: invokestatic 288	cn/jpush/android/util/x:e	()V
    //   1404: goto -149 -> 1255
    //   1407: astore 18
    //   1409: aload 17
    //   1411: ifnull -144 -> 1267
    //   1414: aload 17
    //   1416: invokeinterface 318 1 0
    //   1421: goto -154 -> 1267
    //   1424: astore 18
    //   1426: aconst_null
    //   1427: astore 17
    //   1429: aload 17
    //   1431: ifnull +10 -> 1441
    //   1434: aload 17
    //   1436: invokeinterface 318 1 0
    //   1441: aload 18
    //   1443: athrow
    //   1444: new 146	java/lang/StringBuilder
    //   1447: dup
    //   1448: getstatic 111	cn/jpush/android/service/o:z	[Ljava/lang/String;
    //   1451: bipush 21
    //   1453: aaload
    //   1454: invokespecial 238	java/lang/StringBuilder:<init>	(Ljava/lang/String;)V
    //   1457: aload 20
    //   1459: invokevirtual 165	java/lang/StringBuilder:append	(Ljava/lang/String;)Ljava/lang/StringBuilder;
    //   1462: getstatic 111	cn/jpush/android/service/o:z	[Ljava/lang/String;
    //   1465: iconst_4
    //   1466: aaload
    //   1467: invokevirtual 165	java/lang/StringBuilder:append	(Ljava/lang/String;)Ljava/lang/StringBuilder;
    //   1470: invokevirtual 168	java/lang/StringBuilder:toString	()Ljava/lang/String;
    //   1473: pop
    //   1474: invokestatic 248	cn/jpush/android/util/x:d	()V
    //   1477: aload 19
    //   1479: aload 20
    //   1481: aload 18
    //   1483: invokestatic 232	cn/jpush/android/service/PushService:b	()Ljava/lang/String;
    //   1486: invokestatic 235	cn/jpush/android/util/a:d	()Ljava/lang/String;
    //   1489: new 146	java/lang/StringBuilder
    //   1492: dup
    //   1493: invokespecial 225	java/lang/StringBuilder:<init>	()V
    //   1496: iload 8
    //   1498: invokevirtual 230	java/lang/StringBuilder:append	(I)Ljava/lang/StringBuilder;
    //   1501: invokevirtual 168	java/lang/StringBuilder:toString	()Ljava/lang/String;
    //   1504: iload 4
    //   1506: iconst_1
    //   1507: iload 5
    //   1509: iload 6
    //   1511: iload 7
    //   1513: iconst_0
    //   1514: invokevirtual 326	cn/jpush/android/data/u:a	(Ljava/lang/String;Ljava/lang/String;Ljava/lang/String;Ljava/lang/String;Ljava/lang/String;IIIIII)J
    //   1517: pop2
    //   1518: goto -251 -> 1267
    //   1521: iconst_m1
    //   1522: istore_2
    //   1523: goto -248 -> 1275
    //   1526: astore 18
    //   1528: goto -99 -> 1429
    //   1531: astore 17
    //   1533: aconst_null
    //   1534: astore 17
    //   1536: goto -127 -> 1409
    //
    // Exception table:
    //   from	to	target	type
    //   1163	1166	1407	java/lang/Exception
    //   1166	1173	1407	java/lang/Exception
    //   1178	1255	1407	java/lang/Exception
    //   1401	1404	1407	java/lang/Exception
    //   1149	1158	1424	finally
    //   1163	1166	1526	finally
    //   1166	1173	1526	finally
    //   1178	1255	1526	finally
    //   1401	1404	1526	finally
    //   1149	1158	1531	java/lang/Exception
  }

  // ERROR //
  public final void run()
  {
    // Byte code:
    //   0: new 146	java/lang/StringBuilder
    //   3: dup
    //   4: getstatic 111	cn/jpush/android/service/o:z	[Ljava/lang/String;
    //   7: bipush 34
    //   9: aaload
    //   10: invokespecial 238	java/lang/StringBuilder:<init>	(Ljava/lang/String;)V
    //   13: aload_0
    //   14: invokevirtual 332	cn/jpush/android/service/o:getId	()J
    //   17: invokevirtual 241	java/lang/StringBuilder:append	(J)Ljava/lang/StringBuilder;
    //   20: invokevirtual 168	java/lang/StringBuilder:toString	()Ljava/lang/String;
    //   23: pop
    //   24: invokestatic 248	cn/jpush/android/util/x:d	()V
    //   27: aload_0
    //   28: getfield 115	cn/jpush/android/service/o:b	Lcn/jpush/android/service/PushService;
    //   31: astore_2
    //   32: invokestatic 335	cn/jpush/android/service/PushService:c	()Z
    //   35: pop
    //   36: aload_0
    //   37: getfield 115	cn/jpush/android/service/o:b	Lcn/jpush/android/service/PushService;
    //   40: getfield 202	cn/jpush/android/service/PushService:w	J
    //   43: lconst_0
    //   44: lcmp
    //   45: ifeq +24 -> 69
    //   48: invokestatic 288	cn/jpush/android/util/x:e	()V
    //   51: aload_0
    //   52: getfield 115	cn/jpush/android/service/o:b	Lcn/jpush/android/service/PushService;
    //   55: aload_0
    //   56: getfield 115	cn/jpush/android/service/o:b	Lcn/jpush/android/service/PushService;
    //   59: getfield 202	cn/jpush/android/service/PushService:w	J
    //   62: invokestatic 339	cn/jpush/android/service/PushProtocol:Close	(J)I
    //   65: i2l
    //   66: putfield 202	cn/jpush/android/service/PushService:w	J
    //   69: iconst_0
    //   70: putstatic 343	cn/jpush/android/service/PushService:E	I
    //   73: aload_0
    //   74: getfield 115	cn/jpush/android/service/o:b	Lcn/jpush/android/service/PushService;
    //   77: iconst_0
    //   78: invokevirtual 346	cn/jpush/android/service/PushService:e	(Z)V
    //   81: aload_0
    //   82: getfield 115	cn/jpush/android/service/o:b	Lcn/jpush/android/service/PushService;
    //   85: invokestatic 349	cn/jpush/android/service/PushProtocol:InitConn	()J
    //   88: putfield 202	cn/jpush/android/service/PushService:w	J
    //   91: aload_0
    //   92: getfield 115	cn/jpush/android/service/o:b	Lcn/jpush/android/service/PushService;
    //   95: invokestatic 352	cn/jpush/android/service/PushService:a	(Lcn/jpush/android/service/PushService;)I
    //   98: istore_1
    //   99: iload_1
    //   100: ifeq +78 -> 178
    //   103: new 146	java/lang/StringBuilder
    //   106: dup
    //   107: getstatic 111	cn/jpush/android/service/o:z	[Ljava/lang/String;
    //   110: bipush 40
    //   112: aaload
    //   113: invokespecial 238	java/lang/StringBuilder:<init>	(Ljava/lang/String;)V
    //   116: aload_0
    //   117: invokevirtual 332	cn/jpush/android/service/o:getId	()J
    //   120: invokevirtual 241	java/lang/StringBuilder:append	(J)Ljava/lang/StringBuilder;
    //   123: invokevirtual 168	java/lang/StringBuilder:toString	()Ljava/lang/String;
    //   126: pop
    //   127: invokestatic 181	cn/jpush/android/util/x:c	()V
    //   130: aload_0
    //   131: getfield 115	cn/jpush/android/service/o:b	Lcn/jpush/android/service/PushService;
    //   134: getfield 202	cn/jpush/android/service/PushService:w	J
    //   137: lconst_0
    //   138: lcmp
    //   139: ifeq +24 -> 163
    //   142: invokestatic 288	cn/jpush/android/util/x:e	()V
    //   145: aload_0
    //   146: getfield 115	cn/jpush/android/service/o:b	Lcn/jpush/android/service/PushService;
    //   149: aload_0
    //   150: getfield 115	cn/jpush/android/service/o:b	Lcn/jpush/android/service/PushService;
    //   153: getfield 202	cn/jpush/android/service/PushService:w	J
    //   156: invokestatic 339	cn/jpush/android/service/PushProtocol:Close	(J)I
    //   159: i2l
    //   160: putfield 202	cn/jpush/android/service/PushService:w	J
    //   163: aload_0
    //   164: getfield 115	cn/jpush/android/service/o:b	Lcn/jpush/android/service/PushService;
    //   167: invokevirtual 354	cn/jpush/android/service/PushService:g	()V
    //   170: return
    //   171: astore_2
    //   172: invokestatic 181	cn/jpush/android/util/x:c	()V
    //   175: goto -106 -> 69
    //   178: getstatic 111	cn/jpush/android/service/o:z	[Ljava/lang/String;
    //   181: bipush 38
    //   183: aaload
    //   184: iconst_1
    //   185: anewarray 151	java/lang/Object
    //   188: dup
    //   189: iconst_0
    //   190: iload_1
    //   191: invokestatic 323	java/lang/Integer:valueOf	(I)Ljava/lang/Integer;
    //   194: aastore
    //   195: invokestatic 161	java/lang/String:format	(Ljava/lang/String;[Ljava/lang/Object;)Ljava/lang/String;
    //   198: pop
    //   199: invokestatic 181	cn/jpush/android/util/x:c	()V
    //   202: invokestatic 356	cn/jpush/android/service/PushService:h	()Z
    //   205: ifne +17 -> 222
    //   208: aload_0
    //   209: getfield 115	cn/jpush/android/service/o:b	Lcn/jpush/android/service/PushService;
    //   212: invokevirtual 206	cn/jpush/android/service/PushService:getApplicationContext	()Landroid/content/Context;
    //   215: invokestatic 359	cn/jpush/android/service/PushService:c	(Landroid/content/Context;)Z
    //   218: invokestatic 362	cn/jpush/android/service/PushService:f	(Z)Z
    //   221: pop
    //   222: invokestatic 356	cn/jpush/android/service/PushService:h	()Z
    //   225: ifeq +23 -> 248
    //   228: getstatic 172	cn/jpush/android/service/PushService:t	J
    //   231: lconst_0
    //   232: lcmp
    //   233: ifeq +15 -> 248
    //   236: getstatic 136	cn/jpush/android/service/PushService:u	Ljava/lang/String;
    //   239: ifnull +9 -> 248
    //   242: getstatic 365	cn/jpush/android/a:l	Z
    //   245: ifeq +300 -> 545
    //   248: aload_0
    //   249: getfield 115	cn/jpush/android/service/o:b	Lcn/jpush/android/service/PushService;
    //   252: invokevirtual 366	cn/jpush/android/service/PushService:d	()V
    //   255: getstatic 172	cn/jpush/android/service/PushService:t	J
    //   258: lconst_0
    //   259: lcmp
    //   260: ifeq +360 -> 620
    //   263: aload_0
    //   264: invokespecial 368	cn/jpush/android/service/o:a	()I
    //   267: istore_1
    //   268: iload_1
    //   269: ifeq +10 -> 279
    //   272: iload_1
    //   273: sipush 9999
    //   276: if_icmpne +276 -> 552
    //   279: getstatic 111	cn/jpush/android/service/o:z	[Ljava/lang/String;
    //   282: bipush 25
    //   284: aaload
    //   285: new 146	java/lang/StringBuilder
    //   288: dup
    //   289: getstatic 111	cn/jpush/android/service/o:z	[Ljava/lang/String;
    //   292: bipush 36
    //   294: aaload
    //   295: invokespecial 238	java/lang/StringBuilder:<init>	(Ljava/lang/String;)V
    //   298: aload_0
    //   299: getfield 115	cn/jpush/android/service/o:b	Lcn/jpush/android/service/PushService;
    //   302: invokevirtual 206	cn/jpush/android/service/PushService:getApplicationContext	()Landroid/content/Context;
    //   305: invokestatic 370	cn/jpush/android/util/a:t	(Landroid/content/Context;)Ljava/lang/String;
    //   308: invokevirtual 165	java/lang/StringBuilder:append	(Ljava/lang/String;)Ljava/lang/StringBuilder;
    //   311: invokevirtual 168	java/lang/StringBuilder:toString	()Ljava/lang/String;
    //   314: invokestatic 372	cn/jpush/android/util/x:b	(Ljava/lang/String;Ljava/lang/String;)V
    //   317: aload_0
    //   318: getfield 115	cn/jpush/android/service/o:b	Lcn/jpush/android/service/PushService;
    //   321: iconst_0
    //   322: invokestatic 375	cn/jpush/android/service/PushService:a	(Lcn/jpush/android/service/PushService;I)I
    //   325: pop
    //   326: invokestatic 377	cn/jpush/android/service/PushService:i	()Z
    //   329: ifeq +10 -> 339
    //   332: aload_0
    //   333: getfield 115	cn/jpush/android/service/o:b	Lcn/jpush/android/service/PushService;
    //   336: invokestatic 379	cn/jpush/android/service/PushService:b	(Lcn/jpush/android/service/PushService;)V
    //   339: aload_0
    //   340: getfield 115	cn/jpush/android/service/o:b	Lcn/jpush/android/service/PushService;
    //   343: invokevirtual 381	cn/jpush/android/service/PushService:f	()V
    //   346: iload_1
    //   347: sipush 9999
    //   350: if_icmpne +13 -> 363
    //   353: aload_0
    //   354: getfield 115	cn/jpush/android/service/o:b	Lcn/jpush/android/service/PushService;
    //   357: sipush 6000
    //   360: invokestatic 384	cn/jpush/android/service/PushService:b	(Lcn/jpush/android/service/PushService;I)V
    //   363: aload_0
    //   364: getfield 115	cn/jpush/android/service/o:b	Lcn/jpush/android/service/PushService;
    //   367: iconst_1
    //   368: getstatic 111	cn/jpush/android/service/o:z	[Ljava/lang/String;
    //   371: bipush 32
    //   373: aaload
    //   374: invokevirtual 387	cn/jpush/android/service/PushService:a	(ILjava/lang/String;)V
    //   377: aload_0
    //   378: getfield 119	cn/jpush/android/service/o:c	Z
    //   381: ifne +86 -> 467
    //   384: aload_0
    //   385: getfield 115	cn/jpush/android/service/o:b	Lcn/jpush/android/service/PushService;
    //   388: getfield 202	cn/jpush/android/service/PushService:w	J
    //   391: aload_0
    //   392: getfield 115	cn/jpush/android/service/o:b	Lcn/jpush/android/service/PushService;
    //   395: getfield 391	cn/jpush/android/service/PushService:x	[B
    //   398: ldc_w 392
    //   401: invokestatic 396	cn/jpush/android/service/PushProtocol:RecvPush	(J[BI)I
    //   404: istore_1
    //   405: getstatic 111	cn/jpush/android/service/o:z	[Ljava/lang/String;
    //   408: bipush 37
    //   410: aaload
    //   411: iconst_1
    //   412: anewarray 151	java/lang/Object
    //   415: dup
    //   416: iconst_0
    //   417: iload_1
    //   418: invokestatic 323	java/lang/Integer:valueOf	(I)Ljava/lang/Integer;
    //   421: aastore
    //   422: invokestatic 161	java/lang/String:format	(Ljava/lang/String;[Ljava/lang/Object;)Ljava/lang/String;
    //   425: pop
    //   426: invokestatic 181	cn/jpush/android/util/x:c	()V
    //   429: iload_1
    //   430: ifle +229 -> 659
    //   433: invokestatic 377	cn/jpush/android/service/PushService:i	()Z
    //   436: ifeq +10 -> 446
    //   439: aload_0
    //   440: getfield 115	cn/jpush/android/service/o:b	Lcn/jpush/android/service/PushService;
    //   443: invokestatic 379	cn/jpush/android/service/PushService:b	(Lcn/jpush/android/service/PushService;)V
    //   446: aload_0
    //   447: getfield 115	cn/jpush/android/service/o:b	Lcn/jpush/android/service/PushService;
    //   450: iload_1
    //   451: invokevirtual 398	cn/jpush/android/service/PushService:e	(I)V
    //   454: ldc2_w 399
    //   457: invokestatic 404	java/lang/Thread:sleep	(J)V
    //   460: goto -83 -> 377
    //   463: astore_2
    //   464: invokestatic 406	cn/jpush/android/util/x:h	()V
    //   467: aload_0
    //   468: iconst_0
    //   469: putfield 121	cn/jpush/android/service/o:a	Z
    //   472: new 146	java/lang/StringBuilder
    //   475: dup
    //   476: getstatic 111	cn/jpush/android/service/o:z	[Ljava/lang/String;
    //   479: bipush 39
    //   481: aaload
    //   482: invokespecial 238	java/lang/StringBuilder:<init>	(Ljava/lang/String;)V
    //   485: aload_0
    //   486: invokevirtual 332	cn/jpush/android/service/o:getId	()J
    //   489: invokevirtual 241	java/lang/StringBuilder:append	(J)Ljava/lang/StringBuilder;
    //   492: invokevirtual 168	java/lang/StringBuilder:toString	()Ljava/lang/String;
    //   495: pop
    //   496: invokestatic 407	cn/jpush/android/util/x:b	()V
    //   499: aload_0
    //   500: getfield 115	cn/jpush/android/service/o:b	Lcn/jpush/android/service/PushService;
    //   503: getfield 202	cn/jpush/android/service/PushService:w	J
    //   506: lconst_0
    //   507: lcmp
    //   508: ifeq +24 -> 532
    //   511: invokestatic 288	cn/jpush/android/util/x:e	()V
    //   514: aload_0
    //   515: getfield 115	cn/jpush/android/service/o:b	Lcn/jpush/android/service/PushService;
    //   518: aload_0
    //   519: getfield 115	cn/jpush/android/service/o:b	Lcn/jpush/android/service/PushService;
    //   522: getfield 202	cn/jpush/android/service/PushService:w	J
    //   525: invokestatic 339	cn/jpush/android/service/PushProtocol:Close	(J)I
    //   528: i2l
    //   529: putfield 202	cn/jpush/android/service/PushService:w	J
    //   532: aload_0
    //   533: getfield 115	cn/jpush/android/service/o:b	Lcn/jpush/android/service/PushService;
    //   536: invokevirtual 354	cn/jpush/android/service/PushService:g	()V
    //   539: return
    //   540: astore_2
    //   541: invokestatic 406	cn/jpush/android/util/x:h	()V
    //   544: return
    //   545: iconst_1
    //   546: putstatic 409	cn/jpush/android/a:j	Z
    //   549: goto -294 -> 255
    //   552: getstatic 111	cn/jpush/android/service/o:z	[Ljava/lang/String;
    //   555: bipush 25
    //   557: aaload
    //   558: new 146	java/lang/StringBuilder
    //   561: dup
    //   562: getstatic 111	cn/jpush/android/service/o:z	[Ljava/lang/String;
    //   565: bipush 35
    //   567: aaload
    //   568: invokespecial 238	java/lang/StringBuilder:<init>	(Ljava/lang/String;)V
    //   571: aload_0
    //   572: getfield 115	cn/jpush/android/service/o:b	Lcn/jpush/android/service/PushService;
    //   575: getfield 202	cn/jpush/android/service/PushService:w	J
    //   578: invokestatic 413	cn/jpush/android/service/PushProtocol:GetEsg	(J)Ljava/lang/String;
    //   581: invokevirtual 165	java/lang/StringBuilder:append	(Ljava/lang/String;)Ljava/lang/StringBuilder;
    //   584: invokevirtual 168	java/lang/StringBuilder:toString	()Ljava/lang/String;
    //   587: invokestatic 372	cn/jpush/android/util/x:b	(Ljava/lang/String;Ljava/lang/String;)V
    //   590: iload_1
    //   591: ifle +13 -> 604
    //   594: aload_0
    //   595: getfield 115	cn/jpush/android/service/o:b	Lcn/jpush/android/service/PushService;
    //   598: invokevirtual 414	cn/jpush/android/service/PushService:e	()V
    //   601: goto -102 -> 499
    //   604: iload_1
    //   605: ifge -106 -> 499
    //   608: aload_0
    //   609: getfield 115	cn/jpush/android/service/o:b	Lcn/jpush/android/service/PushService;
    //   612: lconst_0
    //   613: invokestatic 417	cn/jpush/android/service/PushService:a	(Lcn/jpush/android/service/PushService;J)J
    //   616: pop2
    //   617: goto -118 -> 499
    //   620: getstatic 111	cn/jpush/android/service/o:z	[Ljava/lang/String;
    //   623: bipush 25
    //   625: aaload
    //   626: new 146	java/lang/StringBuilder
    //   629: dup
    //   630: getstatic 111	cn/jpush/android/service/o:z	[Ljava/lang/String;
    //   633: bipush 33
    //   635: aaload
    //   636: invokespecial 238	java/lang/StringBuilder:<init>	(Ljava/lang/String;)V
    //   639: aload_0
    //   640: invokevirtual 332	cn/jpush/android/service/o:getId	()J
    //   643: invokevirtual 241	java/lang/StringBuilder:append	(J)Ljava/lang/StringBuilder;
    //   646: invokevirtual 168	java/lang/StringBuilder:toString	()Ljava/lang/String;
    //   649: invokestatic 372	cn/jpush/android/util/x:b	(Ljava/lang/String;Ljava/lang/String;)V
    //   652: goto -153 -> 499
    //   655: astore_2
    //   656: goto -310 -> 346
    //   659: iload_1
    //   660: sipush -994
    //   663: if_icmpne -196 -> 467
    //   666: goto -212 -> 454
    //
    // Exception table:
    //   from	to	target	type
    //   36	69	171	java/lang/Exception
    //   454	460	463	java/lang/InterruptedException
    //   69	99	540	java/lang/Exception
    //   103	163	540	java/lang/Exception
    //   163	170	540	java/lang/Exception
    //   178	222	540	java/lang/Exception
    //   222	248	540	java/lang/Exception
    //   248	255	540	java/lang/Exception
    //   255	268	540	java/lang/Exception
    //   279	339	540	java/lang/Exception
    //   353	363	540	java/lang/Exception
    //   363	377	540	java/lang/Exception
    //   377	429	540	java/lang/Exception
    //   433	446	540	java/lang/Exception
    //   446	454	540	java/lang/Exception
    //   454	460	540	java/lang/Exception
    //   464	467	540	java/lang/Exception
    //   467	499	540	java/lang/Exception
    //   499	532	540	java/lang/Exception
    //   532	539	540	java/lang/Exception
    //   545	549	540	java/lang/Exception
    //   552	590	540	java/lang/Exception
    //   594	601	540	java/lang/Exception
    //   608	617	540	java/lang/Exception
    //   620	652	540	java/lang/Exception
    //   339	346	655	java/lang/Exception
  }
}

/* Location:           F:\\apk\\jingmgou\jingmgou2\classes-dex2jar.jar
 * Qualified Name:     cn.jpush.android.service.o
 * JD-Core Version:    0.6.2
 */