package com.baidu.location.b;

class r extends Thread
{
  r(m paramm)
  {
  }

  // ERROR //
  public void run()
  {
    // Byte code:
    //   0: aload_0
    //   1: getfield 10	com/baidu/location/b/r:a	Lcom/baidu/location/b/m;
    //   4: invokestatic 25	com/baidu/location/b/k:Z	()Ljava/lang/String;
    //   7: putfield 31	com/baidu/location/b/m:c5	Ljava/lang/String;
    //   10: aload_0
    //   11: getfield 10	com/baidu/location/b/r:a	Lcom/baidu/location/b/m;
    //   14: invokestatic 34	com/baidu/location/b/m:if	(Lcom/baidu/location/b/m;)V
    //   17: aload_0
    //   18: getfield 10	com/baidu/location/b/r:a	Lcom/baidu/location/b/m;
    //   21: invokevirtual 37	com/baidu/location/b/m:au	()V
    //   24: aload_0
    //   25: getfield 10	com/baidu/location/b/r:a	Lcom/baidu/location/b/m;
    //   28: getfield 41	com/baidu/location/b/m:dg	I
    //   31: istore_2
    //   32: getstatic 44	com/baidu/location/b/m:c8	I
    //   35: getstatic 49	com/baidu/location/b/g:byte	I
    //   38: if_icmpne +635 -> 673
    //   41: aconst_null
    //   42: astore 6
    //   44: iconst_1
    //   45: istore_1
    //   46: iload_2
    //   47: ifle +520 -> 567
    //   50: new 51	org/apache/http/client/methods/HttpPost
    //   53: dup
    //   54: aload_0
    //   55: getfield 10	com/baidu/location/b/r:a	Lcom/baidu/location/b/m;
    //   58: getfield 31	com/baidu/location/b/m:c5	Ljava/lang/String;
    //   61: invokespecial 54	org/apache/http/client/methods/HttpPost:<init>	(Ljava/lang/String;)V
    //   64: astore 7
    //   66: iload_1
    //   67: istore_3
    //   68: iload_1
    //   69: istore 4
    //   71: new 56	org/apache/http/client/entity/UrlEncodedFormEntity
    //   74: dup
    //   75: aload_0
    //   76: getfield 10	com/baidu/location/b/r:a	Lcom/baidu/location/b/m;
    //   79: getfield 60	com/baidu/location/b/m:c7	Ljava/util/List;
    //   82: ldc 62
    //   84: invokespecial 65	org/apache/http/client/entity/UrlEncodedFormEntity:<init>	(Ljava/util/List;Ljava/lang/String;)V
    //   87: astore 6
    //   89: iload_1
    //   90: istore_3
    //   91: iload_1
    //   92: istore 4
    //   94: aload 7
    //   96: ldc 67
    //   98: ldc 69
    //   100: invokevirtual 73	org/apache/http/client/methods/HttpPost:setHeader	(Ljava/lang/String;Ljava/lang/String;)V
    //   103: iload_1
    //   104: istore_3
    //   105: iload_1
    //   106: istore 4
    //   108: aload 7
    //   110: ldc 75
    //   112: ldc 77
    //   114: invokevirtual 73	org/apache/http/client/methods/HttpPost:setHeader	(Ljava/lang/String;Ljava/lang/String;)V
    //   117: iload_1
    //   118: istore_3
    //   119: iload_1
    //   120: istore 4
    //   122: aload 7
    //   124: ldc 79
    //   126: ldc 81
    //   128: invokevirtual 73	org/apache/http/client/methods/HttpPost:setHeader	(Ljava/lang/String;Ljava/lang/String;)V
    //   131: iload_1
    //   132: istore_3
    //   133: iload_1
    //   134: istore 4
    //   136: aload 7
    //   138: ldc 83
    //   140: ldc 85
    //   142: invokevirtual 88	org/apache/http/client/methods/HttpPost:addHeader	(Ljava/lang/String;Ljava/lang/String;)V
    //   145: iload_1
    //   146: istore_3
    //   147: iload_1
    //   148: istore 4
    //   150: aload 7
    //   152: aload 6
    //   154: invokevirtual 92	org/apache/http/client/methods/HttpPost:setEntity	(Lorg/apache/http/HttpEntity;)V
    //   157: iload_1
    //   158: istore_3
    //   159: iload_1
    //   160: istore 4
    //   162: new 94	org/apache/http/impl/client/DefaultHttpClient
    //   165: dup
    //   166: invokespecial 95	org/apache/http/impl/client/DefaultHttpClient:<init>	()V
    //   169: astore 6
    //   171: iload_1
    //   172: istore_3
    //   173: iload_1
    //   174: istore 4
    //   176: aload 6
    //   178: invokeinterface 101 1 0
    //   183: ldc 103
    //   185: getstatic 106	com/baidu/location/b/g:Q	I
    //   188: invokestatic 112	java/lang/Integer:valueOf	(I)Ljava/lang/Integer;
    //   191: invokeinterface 118 3 0
    //   196: pop
    //   197: iload_1
    //   198: istore_3
    //   199: iload_1
    //   200: istore 4
    //   202: aload 6
    //   204: invokeinterface 101 1 0
    //   209: ldc 120
    //   211: getstatic 106	com/baidu/location/b/g:Q	I
    //   214: invokestatic 112	java/lang/Integer:valueOf	(I)Ljava/lang/Integer;
    //   217: invokeinterface 118 3 0
    //   222: pop
    //   223: iload_1
    //   224: istore_3
    //   225: iload_1
    //   226: istore 4
    //   228: aload 6
    //   230: invokeinterface 101 1 0
    //   235: iconst_0
    //   236: invokestatic 126	org/apache/http/params/HttpProtocolParams:setUseExpectContinue	(Lorg/apache/http/params/HttpParams;Z)V
    //   239: iload_1
    //   240: ifeq +441 -> 681
    //   243: iload_1
    //   244: istore_3
    //   245: iload_1
    //   246: istore 4
    //   248: new 128	org/apache/http/HttpHost
    //   251: dup
    //   252: invokestatic 131	com/baidu/location/b/m:al	()Ljava/lang/String;
    //   255: invokestatic 135	com/baidu/location/b/m:ar	()I
    //   258: ldc 137
    //   260: invokespecial 140	org/apache/http/HttpHost:<init>	(Ljava/lang/String;ILjava/lang/String;)V
    //   263: astore 8
    //   265: iload_1
    //   266: istore_3
    //   267: iload_1
    //   268: istore 4
    //   270: aload 6
    //   272: invokeinterface 101 1 0
    //   277: ldc 142
    //   279: aload 8
    //   281: invokeinterface 118 3 0
    //   286: pop
    //   287: goto +394 -> 681
    //   290: iload_1
    //   291: istore_3
    //   292: iload_1
    //   293: istore 4
    //   295: aload 6
    //   297: aload 7
    //   299: invokeinterface 146 2 0
    //   304: astore 8
    //   306: iload_1
    //   307: istore_3
    //   308: iload_1
    //   309: istore 4
    //   311: aload 8
    //   313: invokeinterface 152 1 0
    //   318: invokeinterface 157 1 0
    //   323: sipush 200
    //   326: if_icmpne +279 -> 605
    //   329: iload_1
    //   330: istore_3
    //   331: iload_1
    //   332: istore 4
    //   334: aload 8
    //   336: invokeinterface 161 1 0
    //   341: invokeinterface 167 1 0
    //   346: astore 6
    //   348: iload_1
    //   349: istore_3
    //   350: iload_1
    //   351: istore 4
    //   353: aload 8
    //   355: ldc 169
    //   357: invokeinterface 173 2 0
    //   362: astore 8
    //   364: aload 8
    //   366: ifnull +304 -> 670
    //   369: iload_1
    //   370: istore_3
    //   371: iload_1
    //   372: istore 4
    //   374: aload 8
    //   376: invokeinterface 178 1 0
    //   381: ldc 85
    //   383: invokevirtual 184	java/lang/String:equalsIgnoreCase	(Ljava/lang/String;)Z
    //   386: ifeq +284 -> 670
    //   389: iload_1
    //   390: istore_3
    //   391: iload_1
    //   392: istore 4
    //   394: new 186	java/util/zip/GZIPInputStream
    //   397: dup
    //   398: new 188	java/io/BufferedInputStream
    //   401: dup
    //   402: aload 6
    //   404: invokespecial 191	java/io/BufferedInputStream:<init>	(Ljava/io/InputStream;)V
    //   407: invokespecial 192	java/util/zip/GZIPInputStream:<init>	(Ljava/io/InputStream;)V
    //   410: astore 6
    //   412: iload_1
    //   413: istore_3
    //   414: iload_1
    //   415: istore 4
    //   417: new 194	java/io/ByteArrayOutputStream
    //   420: dup
    //   421: invokespecial 195	java/io/ByteArrayOutputStream:<init>	()V
    //   424: astore 9
    //   426: iload_1
    //   427: istore_3
    //   428: iload_1
    //   429: istore 4
    //   431: aload 6
    //   433: invokevirtual 200	java/io/InputStream:read	()I
    //   436: istore 5
    //   438: iload 5
    //   440: iconst_m1
    //   441: if_icmpeq +52 -> 493
    //   444: iload_1
    //   445: istore_3
    //   446: iload_1
    //   447: istore 4
    //   449: aload 9
    //   451: iload 5
    //   453: invokevirtual 204	java/io/ByteArrayOutputStream:write	(I)V
    //   456: goto -30 -> 426
    //   459: astore 6
    //   461: aload 7
    //   463: astore 6
    //   465: iload_3
    //   466: istore_1
    //   467: aload 6
    //   469: invokevirtual 207	org/apache/http/client/methods/HttpPost:abort	()V
    //   472: getstatic 210	com/baidu/location/b/g:m	Ljava/lang/String;
    //   475: ldc 212
    //   477: invokestatic 218	android/util/Log:d	(Ljava/lang/String;Ljava/lang/String;)I
    //   480: pop
    //   481: iload_2
    //   482: iconst_1
    //   483: isub
    //   484: istore_2
    //   485: goto -439 -> 46
    //   488: iconst_0
    //   489: istore_1
    //   490: goto -200 -> 290
    //   493: iload_1
    //   494: istore_3
    //   495: iload_1
    //   496: istore 4
    //   498: aload 9
    //   500: invokevirtual 221	java/io/ByteArrayOutputStream:toString	()Ljava/lang/String;
    //   503: astore 8
    //   505: aload 6
    //   507: ifnull +11 -> 518
    //   510: iload_1
    //   511: istore 4
    //   513: aload 6
    //   515: invokevirtual 224	java/io/InputStream:close	()V
    //   518: aload 9
    //   520: ifnull +11 -> 531
    //   523: iload_1
    //   524: istore 4
    //   526: aload 9
    //   528: invokevirtual 225	java/io/ByteArrayOutputStream:close	()V
    //   531: iload_1
    //   532: istore_3
    //   533: iload_1
    //   534: istore 4
    //   536: aload_0
    //   537: getfield 10	com/baidu/location/b/r:a	Lcom/baidu/location/b/m;
    //   540: new 227	org/apache/http/entity/StringEntity
    //   543: dup
    //   544: aload 8
    //   546: ldc 229
    //   548: invokespecial 231	org/apache/http/entity/StringEntity:<init>	(Ljava/lang/String;Ljava/lang/String;)V
    //   551: putfield 235	com/baidu/location/b/m:c6	Lorg/apache/http/HttpEntity;
    //   554: iload_1
    //   555: istore_3
    //   556: iload_1
    //   557: istore 4
    //   559: aload_0
    //   560: getfield 10	com/baidu/location/b/r:a	Lcom/baidu/location/b/m;
    //   563: iconst_1
    //   564: invokevirtual 239	com/baidu/location/b/m:int	(Z)V
    //   567: iload_2
    //   568: ifgt +80 -> 648
    //   571: getstatic 242	com/baidu/location/b/m:de	I
    //   574: iconst_1
    //   575: iadd
    //   576: putstatic 242	com/baidu/location/b/m:de	I
    //   579: aload_0
    //   580: getfield 10	com/baidu/location/b/r:a	Lcom/baidu/location/b/m;
    //   583: aconst_null
    //   584: putfield 235	com/baidu/location/b/m:c6	Lorg/apache/http/HttpEntity;
    //   587: aload_0
    //   588: getfield 10	com/baidu/location/b/r:a	Lcom/baidu/location/b/m;
    //   591: iconst_0
    //   592: invokevirtual 239	com/baidu/location/b/m:int	(Z)V
    //   595: aload_0
    //   596: getfield 10	com/baidu/location/b/r:a	Lcom/baidu/location/b/m;
    //   599: iconst_0
    //   600: invokestatic 245	com/baidu/location/b/m:if	(Lcom/baidu/location/b/m;Z)Z
    //   603: pop
    //   604: return
    //   605: iload_1
    //   606: istore_3
    //   607: iload_1
    //   608: istore 4
    //   610: aload 7
    //   612: invokevirtual 207	org/apache/http/client/methods/HttpPost:abort	()V
    //   615: aload 7
    //   617: astore 6
    //   619: goto -138 -> 481
    //   622: astore 6
    //   624: aload 7
    //   626: astore 6
    //   628: iload 4
    //   630: istore_1
    //   631: aload 6
    //   633: invokevirtual 207	org/apache/http/client/methods/HttpPost:abort	()V
    //   636: getstatic 210	com/baidu/location/b/g:m	Ljava/lang/String;
    //   639: ldc 212
    //   641: invokestatic 218	android/util/Log:d	(Ljava/lang/String;Ljava/lang/String;)I
    //   644: pop
    //   645: goto -164 -> 481
    //   648: iconst_0
    //   649: putstatic 242	com/baidu/location/b/m:de	I
    //   652: goto -57 -> 595
    //   655: astore 7
    //   657: goto -26 -> 631
    //   660: astore 7
    //   662: goto -195 -> 467
    //   665: astore 6
    //   667: goto -136 -> 531
    //   670: goto -258 -> 412
    //   673: aconst_null
    //   674: astore 6
    //   676: iconst_0
    //   677: istore_1
    //   678: goto -632 -> 46
    //   681: iload_1
    //   682: ifne -194 -> 488
    //   685: iconst_1
    //   686: istore_1
    //   687: goto -397 -> 290
    //
    // Exception table:
    //   from	to	target	type
    //   71	89	459	java/lang/Exception
    //   94	103	459	java/lang/Exception
    //   108	117	459	java/lang/Exception
    //   122	131	459	java/lang/Exception
    //   136	145	459	java/lang/Exception
    //   150	157	459	java/lang/Exception
    //   162	171	459	java/lang/Exception
    //   176	197	459	java/lang/Exception
    //   202	223	459	java/lang/Exception
    //   228	239	459	java/lang/Exception
    //   248	265	459	java/lang/Exception
    //   270	287	459	java/lang/Exception
    //   295	306	459	java/lang/Exception
    //   311	329	459	java/lang/Exception
    //   334	348	459	java/lang/Exception
    //   353	364	459	java/lang/Exception
    //   374	389	459	java/lang/Exception
    //   394	412	459	java/lang/Exception
    //   417	426	459	java/lang/Exception
    //   431	438	459	java/lang/Exception
    //   449	456	459	java/lang/Exception
    //   498	505	459	java/lang/Exception
    //   536	554	459	java/lang/Exception
    //   559	567	459	java/lang/Exception
    //   610	615	459	java/lang/Exception
    //   71	89	622	java/lang/Error
    //   94	103	622	java/lang/Error
    //   108	117	622	java/lang/Error
    //   122	131	622	java/lang/Error
    //   136	145	622	java/lang/Error
    //   150	157	622	java/lang/Error
    //   162	171	622	java/lang/Error
    //   176	197	622	java/lang/Error
    //   202	223	622	java/lang/Error
    //   228	239	622	java/lang/Error
    //   248	265	622	java/lang/Error
    //   270	287	622	java/lang/Error
    //   295	306	622	java/lang/Error
    //   311	329	622	java/lang/Error
    //   334	348	622	java/lang/Error
    //   353	364	622	java/lang/Error
    //   374	389	622	java/lang/Error
    //   394	412	622	java/lang/Error
    //   417	426	622	java/lang/Error
    //   431	438	622	java/lang/Error
    //   449	456	622	java/lang/Error
    //   498	505	622	java/lang/Error
    //   513	518	622	java/lang/Error
    //   526	531	622	java/lang/Error
    //   536	554	622	java/lang/Error
    //   559	567	622	java/lang/Error
    //   610	615	622	java/lang/Error
    //   50	66	655	java/lang/Error
    //   50	66	660	java/lang/Exception
    //   513	518	665	java/lang/Exception
    //   526	531	665	java/lang/Exception
  }
}

/* Location:           F:\一周备份\面试apk\希望代码没混淆\jingmgou\jingmgou2\classes-dex2jar.jar
 * Qualified Name:     com.baidu.location.b.r
 * JD-Core Version:    0.6.2
 */